_pynix.so
libpynix-0.1.0.dist-info/RECORD
libpynix-0.1.0.dist-info/METADATA
libpynix-0.1.0.dist-info/top_level.txt
libpynix-0.1.0.dist-info/LICENSE
libpynix-0.1.0.dist-info/WHEEL
pynix/__main__.py
pynix/__init__.py
pynix/tests.py
