Metadata-Version: 1.1
Name: libpynix
Version: 0.1.0
Summary: Extension module which exposes several linux-specific system APIs
Home-page: https://github.com/cheshirekow/pynix
Author: Josh Bialkowski
Author-email: josh.bialkowski@gmail.com
License: GPLv3
Download-URL: https://github.com/cheshirekow/pynix/archive/0.1.0.tar.gz
Keywords: linux,extension-module
Platform: UNKNOWN
Classifier: Development Status :: 3 - Alpha
Classifier: Intended Audience :: Developers
Classifier: License :: OSI Approved :: GNU General Public License v3 (GPLv3)
